LICENSE.txt
MANIFEST.in
README.rst
setup.py
translations/__init__.py
translations/apps.py
translations/models.py
translations.egg-info/PKG-INFO
translations.egg-info/SOURCES.txt
translations.egg-info/dependency_links.txt
translations.egg-info/top_level.txt
translations/migrations/0001_initial.py
translations/migrations/__init__.py
translations/templatetags/__init__.py
translations/templatetags/translate.py